[
  {
    "name": "left-reversedNumpad"
  },
  [
    {
      "x": 4.5
    },
    "ESC",
    "F1",
    "F2",
    "F3",
    "F4",
    "F5",
    "F6"
  ],
  [
    {
      "y": 0.25
    },
    "Back\n\n\n\n\n\nspace",
    "/",
    "*",
    "-",
    {
      "x": 0.5
    },
    "~\n`",
    "!\n1",
    "@\n2",
    "#\n3",
    "$\n4",
    "%\n5",
    "^\n6"
  ],
  [
    {
      "h": 2
    },
    "+",
    "7",
    "8",
    "9",
    {
      "x": 0.5,
      "w": 1.5
    },
    "Tab",
    "Q",
    "W",
    "E",
    "R",
    "T"
  ],
  [
    {
      "x": 1
    },
    "4",
    "5",
    "6",
    {
      "x": 0.5,
      "w": 1.75
    },
    "Fn",
    "A",
    "S",
    "D",
    "F",
    "G"
  ],
  [
    {
      "h": 2
    },
    "Enter",
    "1",
    "2",
    "3",
    {
      "x": 0.5,
      "w": 2.25
    },
    "Shift",
    "Z",
    "X",
    "C",
    "V",
    "B"
  ],
  [
    {
      "x": 1
    },
    ".",
    {
      "w": 2
    },
    "0",
    {
      "x": 0.5,
      "w": 1.25
    },
    "Ctrl",
    {
      "w": 1.25
    },
    "Fn",
    {
      "w": 1.25
    },
    "Alt",
    {
      "w": 1.25
    },
    "Window",
    {
      "a": 7,
      "w": 2.25
    },
    ""
  ]
]